packtxt/__init__.py
packtxt/cli.py
packtxt/packtxt.py
packtxt-0.1.0.dist-info/LICENSE
packtxt-0.1.0.dist-info/METADATA
packtxt-0.1.0.dist-info/WHEEL
packtxt-0.1.0.dist-info/entry_points.txt
packtxt-0.1.0.dist-info/top_level.txt
packtxt-0.1.0.dist-info/RECORD
