Metadata-Version: 2.1
Name: packtxt
Version: 0.1.0
Summary: A tool to pack and unpack directories to/from .txt files with Git branch support
Home-page: https://github.com/digitaluniverse/packtxt
Author: Matt Daniele
Author-email: contact@mattdaniele.com
Classifier: Programming Language :: Python :: 3
Classifier: License :: OSI Approved :: MIT License
Classifier: Operating System :: OS Independent
Requires-Python: >=3.6
License-File: LICENSE
